.gitignore
MANIFEST.in
README.md
setup.py
multiconfig/__init__.py
multiconfig/backends.py
multiconfig.egg-info/PKG-INFO
multiconfig.egg-info/SOURCES.txt
multiconfig.egg-info/dependency_links.txt
multiconfig.egg-info/requires.txt
multiconfig.egg-info/top_level.txt
tests/test_backend_json.py
tests/test_backend_yaml.py
tests/test_config.py
tests/test_load_many.py