Metadata-Version: 1.0
Name: multiconfig
Version: 0.2
Summary: Hierarchical configuration library for Python, supporting cascading configuration files
Home-page: http://github.com/basementcat/multiconfig
Author: Alec Elton
Author-email: alec.elton@gmail.com
License: UNKNOWN
Platform: UNKNOWN
